flake8_pytestrail.py
flake8_pytestrail-0.2.1.dist-info/entry_points.txt
flake8_pytestrail-0.2.1.dist-info/LICENSE
flake8_pytestrail-0.2.1.dist-info/WHEEL
flake8_pytestrail-0.2.1.dist-info/METADATA
flake8_pytestrail-0.2.1.dist-info/RECORD
